kecutil/__init__.py
kecutil/util.py
kecutil-0.0.1.dist-info/METADATA
kecutil-0.0.1.dist-info/WHEEL
kecutil-0.0.1.dist-info/top_level.txt
kecutil-0.0.1.dist-info/RECORD
